{"points": [{"_index": "wiaty1", "_type": "_doc", "_score": 1.0, "_source": {"name": "G\u00f3ry Z\u0142ote N 50\u00b023.883' , E 16\u00b050.665' Wiata przy podej\u015bciu na Jawornik Wielki. Ogie\u0144: brak miejsca Woda:brak", "type": "wiata", "location": {"lon": "16.844417", "lat": "50.39805"}}, "_id": "aeblr2wBa0yzZ7_GV02w"}, {"_index": "wiaty1", "_type": "_doc", "_score": 1.0, "_source": {"name": "G\u00f3ry Bystrzyckie 50\u00b021'16.6\"N 16\u00b028'13.0\"E Chata mysliwskie (zamknieta, nie pod wynajem) ale kolo niej jest przestronna wiata i miejsce na ognisko. Idac z Pokrzywna zielonym szlakiem na poludniowy- zachod mijamy skrzyzowanie z droga \"Wiecznosc\" a na nastepnym skrecamy w lewo. Chatka jest po lewej stronie, niedaleko za jeziorkiem. Potok niedaleko Ogie\u0144:Tak Woda :potok niedaleko", "type": "wiata", "location": {"lon": "16.470278", "lat": "50.354611"}}, "_id": "bOblr2wBa0yzZ7_GV03W"}, {"_index": "wiaty1", "_type": "_doc", "_score": 1.0, "_source": {"name": "Przedg\u00f3rze Paczkowskie, G\u0142\u00f3wny Szlak Sudecki (okolice wsi B\u0142otnica) 50\u00b028'01.2\"N 16\u00b055'58.0\"E. Wiata ko\u0142a \u0142owieckiego, znajduje si\u0119 kilkaset metr\u00f3w od wioski, w lesie, w kierunku Koloni B\u0142otnica. Wiata mo\u017ce pomie\u015bci\u0107 kilkadziesi\u0105t os\u00f3b! Jest nawet murowany kominek Woda brak.", "type": "wiata", "location": {"lon": "16.932778", "lat": "50.467"}}, "_id": "rublr2wBa0yzZ7_GWk2v"}, {"_index": "wiaty1", "_type": "_doc", "_score": 1.0, "_source": {"name": "Wiata pod czerwonym szlakiem na trasie dawnej kolejki sowiog\u00f3rskiej. Prowizoryczne miejsce na ognisko. Brak dost\u0119pu do wody. Wiata ma \u0142aweczki. Jest dobrze zas\u0142oni\u0119ta od wiatru poniewa\u017c znajduje sie w w\u0105wozie. Dosta\u0107 mo\u017cna si\u0119 albo po prostu id\u0105c szlakiem dawnej kolejki albo (jesli jeste\u015bmy na szlaku GSS) schodz\u0105c z mostu w d\u00f3\u0142 nibyschodkami.", "type": "wiata", "location": {"lon": "16.6363", "lat": "50.570689"}}, "_id": "Oeblr2wBa0yzZ7_GX044"}, {"_index": "wiaty1", "_type": "_doc", "_score": 1.0, "_source": {"name": "Wie\u017ca widokowa + wiata obok z miejscem na ognisko . Z wod\u0105 nie wiem jak mia\u0142em swoj\u0105. Nowa Ruda - S\u0142upiec.", "type": "wiata", "location": {"lon": "16.521111", "lat": "50.550851"}}, "_id": "Q-blr2wBa0yzZ7_GX06C"}, {"_index": "wiaty1", "_type": "_doc", "_score": 1.0, "_source": {"name": "G\u00f3ra \u015bw. Anny jest troszk\u0119 zat\u0142oczona. Wynika to g\u0142\u00f3wnie z tego, \u017ce prawie pod sam\u0105 wie\u017c\u0119 prowadzi droga asfaltowa, wi\u0119c wielu turyst\u00f3w przyje\u017cd\u017ca tam na szybki spacer (a widoki pi\u0119kne, wi\u0119c i du\u017co luda). Dlatego polecam t\u0119 miejsc\u00f3wk\u0119 raczej na wypadki w stylu na wszelki wypadek ;). Jest miejsce na ognisko. S\u0105 cztery stoliki pod daszkiem. W \u015brodku wie\u017cy mozna znale\u017a\u0107 kawa\u0142ek p\u0142askiego miejsca na kamieniach.", "type": "wiata", "location": {"lon": "16.500663", "lat": "50.564808"}}, "_id": "bublr2wBa0yzZ7_GYU4i"}, {"_index": "wiaty1", "_type": "_doc", "_score": 1.0, "_source": {"name": "Aby doj\u015b\u0107 do kazamatki nale\u017cy z czerwonego szlaku (przy tablicy Fortu Rogowego) zej\u015b\u0107 w bok na wydeptan\u0105 \u015bcie\u017ck\u0119, kt\u00f3ra idzie dalej dooko\u0142a fosy przy twierdzy. Kazamata znajduje si\u0119 okolo 50-70m od skrzy\u017cowania z czerwonym szlakiem. Jest po prawej stronie drogi, zej\u015bcie jest ostro w d\u00f3\u0142, jakie\u015b 3m od tej \u015bcie\u017cki. Tych kazamat jest w tym miejscu bardzo du\u017co, ale w\u0142a\u015bciwie tylko ta si\u0119 nadaje na nocleg. Reszta jest zasypana i zagruzowana. Nie ma pod\u0142ogi z kamienia, jest to bardziej klepisko. Co wa\u017cne, w tym pomieszczeniu sufit jest bardzo stabilny (fot.5). Wiadomo, \u017ce nale\u017cy uwa\u017ca\u0107 na wszelkie od\u0142amki cegie\u0142 i kamieni, szczeg\u00f3lnie je\u015bli kto\u015b stoi na g\u00f3rze i mo\u017ce komu\u015b spa\u015b\u0107 niechc\u0105cy kamol na g\u0142ow\u0119. Co si\u0119 tyczy jeszcze bezpiecze\u0144stwa, nale\u017cy uwa\u017ca\u0107 szczeg\u00f3lnie w nocy jak si\u0119 wychodzi na sikunde - jakie\u015b 7m dalej jest fosa twierdzy, kt\u00f3ra ogolnie jest bardzo g\u0142\u0119boka (w tym miejscu nie a\u017c tak, ale zawsze). Co do ilo\u015bci os\u00f3b, kt\u00f3re mog\u0105 sie tam zmie\u015bci\u0107 - raz spa\u0142a tam moja znajoma dru\u017cyna harcerzy i zamie\u015bcili si\u0119 wszyscy :). Miejsce na ognisko jakie\u015b prowizoryczne si\u0119 znajdzie.", "type": "wiata", "location": {"lon": "16.637255", "lat": "50.573739"}}, "_id": "cublr2wBa0yzZ7_GYU5E"}, {"_index": "wiaty1", "_type": "_doc", "_score": 1.0, "_source": {"name": "Fort Fryderyka Czarny szlak i serduszkowy szlak w drodze na Kamienn\u0105 G\u00f3r\u0119. 50.37695N 16.48935E Nie eksplorowa\u0142am zbyt dobrze tego miejsca, mo\u017ce s\u0105 jeszcze jakie\u015b korytarze w bliskiej odleg\u0142o\u015bci. Miejsce, kt\u00f3re znalaz\u0142am jest praktycznie dla jednej maks dwoch os\u00f3b. Fort sklada sie w\u0142a\u015bciwie tylko z jednego korytarzyka, do kt\u00f3rego wchodzi si\u0119 jakby pod ziemi\u0119. Sufit w dobrym stanie. Nale\u017cy uwa\u017ca\u0107 na dziury w ziemi (fotka2). Miejsce na ognisko i wody brak. Wiecej historii o tym ciekawym miejscu: https://pl.m.wikipedia.org/wiki/Fort_Fryderyka", "type": "wiata", "location": {"lon": "16.48935", "lat": "50.37695"}}, "_id": "h-blr2wBa0yzZ7_GYU7u"}, {"_index": "wiaty1", "_type": "_doc", "_score": 1.0, "_source": {"name": "Sudety ognisko woda ok 100 m w dolinie potoku.", "type": "wiata", "location": {"lon": "16.48928", "lat": "50.41593"}}, "_id": "oublr2wBa0yzZ7_GYk7Y"}, {"_index": "wiaty1", "_type": "_doc", "_score": 1.0, "_source": {"name": "Tutaj druga wiatki imprezowe ale na nocleg ok przy tej akurat wody za blisko nie ma", "type": "wiata", "location": {"lon": "16.483933", "lat": "50.408904"}}, "_id": "o-blr2wBa0yzZ7_GYk7g"}, {"_index": "wiaty1", "_type": "_doc", "_score": 1.0, "_source": {"name": "Wiata we wsi Wrzos\u00f3wka niedaleko Bor\u00f3wkowej G\u00f3ry sza\u0142u nie ma ale mo\u017cna rozpali\u0107 ognisko schowa\u0107 si\u0119 przed deszczem niedaleko jest woda namiary GPS 50.380816 N 16.90404462 E", "type": "wiata", "location": {"lon": "16.904045", "lat": "50.380816"}}, "_id": "p-blr2wBa0yzZ7_GY04O"}, {"_index": "wiaty1", "_type": "_doc", "_score": 1.0, "_source": {"name": "Wiata znajduje si\u0119 pod wiaduktem. Poprowadzona jest tam r\u00f3wnie\u017c \u017c\u00f3\u0142ta cyklotrasa MTB Sudety. Jest kosz na \u015bmieci, miejsce na ognisko prowizoryczne i malutki strumyczek obok. Wiata nie jest oslonieta. Jest kilka solidnych \u0142awek.", "type": "wiata", "location": {"lon": "16.661676", "lat": "50.564484"}}, "_id": "zOblr2wBa0yzZ7_GZE4v"}, {"_index": "wiaty1", "_type": "_doc", "_score": 1.0, "_source": {"name": "Wiata znajduje si\u0119 pod wiaduktem. Jest miejsce na ognisko i malutki strumyczek obok, kt\u00f3ry uaktywnia si\u0119 po deszczu. Wiata nie jest oslonieta. Jest kilka \u0142awek. Dach troszeczku dziurawy. Wiata nie osloni\u0119ta.", "type": "wiata", "location": {"lon": "16.646052", "lat": "50.569496"}}, "_id": "zeblr2wBa0yzZ7_GZE43"}, {"_index": "wiaty1", "_type": "_doc", "_score": 1.0, "_source": {"name": "Rychleby / G. Z\u0142ote Prze\u0142\u0119cz R\u00f3\u017caniec - 400 m poni\u017cej przy czerwonym szlaku do Bilej Vody. Wiata dla 2-3 os\u00f3b. Dach niepewny. Naprzeciwko opuszczony dom. Miejsce na ognisko - jest. Woda - \u017ar\u00f3d\u0142o 100m powy\u017cej przy szlaku na prze\u0142\u0119cz. 50.407202, 16.871541", "type": "wiata", "location": {"lon": "16.871541", "lat": "50.407202"}}, "_id": "4-blr2wBa0yzZ7_GZE7j"}, {"_index": "wiaty1", "_type": "_doc", "_score": 1.0, "_source": {"name": "Rychleby / G\u00f3ry Z\u0142ote Leti\u0161t\u011b - skrzy\u017cowanie dr\u00f3g 2 km na p\u0142d-wsch od szczytu Bor\u00f3wkowej, zej\u015bcie szlakiem niebieskim. Solidna wiata, w \u015brodku wysypana drobnym t\u0142uczniem. Dach raczej szczelny; przewiewna, ale miejsce jest os\u0142oni\u0119te od wiatru. Palenisko jest. Ocembrowane \u017ar\u00f3de\u0142ko 200 m na zach. przy drodze (szlak zielony). 50.384271, 16.920240", "type": "wiata", "location": {"lon": "16.92024", "lat": "50.384271"}}, "_id": "5Oblr2wBa0yzZ7_GZE7q"}, {"_index": "wiaty1", "_type": "_doc", "_score": 1.0, "_source": {"name": "Du\u017ca wiata z komikniem i \u0142awami. Woda w potoku nieopodal. Obok \u015bmietnik, a nawet niewielki plac zabaw dla dzieci. Miejsce doclegowa dla 5-6 os\u00f3b GPS: 50\u00b022'13.7\"N 16\u00b059'53.1\"E", "type": "wiata", "location": {"lon": "16.998083", "lat": "50.370472"}}, "_id": "9Oblr2wBa0yzZ7_GZU5b"}, {"_index": "wiaty1", "_type": "_doc", "_score": 1.0, "_source": {"name": "Dwie wiaty przy parkingu, mo\u017cliwy dojazd autem, obok strumie\u0144 Czerwona woda (woda ruda- bagienna!). Nie zauwa\u017cono zakazu biwakowania. 50.449630, 16.422661", "type": "wiata", "location": {"lon": "16.422661", "lat": "50.44963"}}, "_id": "Teblr2wBa0yzZ7_GZ0_j"}, {"_index": "wiaty1", "_type": "_doc", "_score": 1.0, "_source": {"name": "Przy le\u015bnej drodze - szlak zielony B\u00edl\u00e1 Voda - Javornik. Bardziej klimatyczne miejsce odpoczynku ni\u017c wiata, ale - jak wida\u0107 - maj\u0105c tarp, mo\u017cna co\u015b skleci\u0107. Woda w potoku tu\u017c obok, miejsce na ognisko i drewno jest. 50.4084761N, 16.8964114E", "type": "wiata", "location": {"lon": "16.8970976", "lat": "50.408476"}}, "_id": "Uublr2wBa0yzZ7_GaE8E"}, {"_index": "wiaty1", "_type": "_doc", "_score": 1.0, "_source": {"name": "opr\u00f3cz tego kima\u0107 mo\u017cna na wie\u017cy; obok ma\u0142e wiatki \u015bniadaniowe, miejsce na ognisko, woda - Bia\u0142a Studnia 50.390542, 16.902301", "type": "wiata", "location": {"lon": "16.902301", "lat": "50.390542"}}, "_id": "VOblr2wBa0yzZ7_GaE8R"}, {"_index": "wiaty1", "_type": "_doc", "_score": 1.0, "_source": {"name": "Wiata odpoczynkowa 50.404667, 16.911310", "type": "wiata", "location": {"lon": "16.91131", "lat": "50.404667"}}, "_id": "Veblr2wBa0yzZ7_GaE8X"}, {"_index": "wiaty1", "_type": "_doc", "_score": 1.0, "_source": {"name": "Wiata z dachem dwuspadowym, wody brak (ewentualnie Czerwona Woda w odleg\u0142o\u015bci ok. 800m). Orientacyjne dane (po\u0142\u0105czenie czerwonego i \u017c\u00f3\u0142tego) 50.457042, 16.428631", "type": "wiata", "location": {"lon": "16.428631", "lat": "50.457042"}}, "_id": "Vublr2wBa0yzZ7_GaE8g"}, {"_index": "wiaty1", "_type": "_doc", "_score": 1.0, "_source": {"name": "G\u00f3ry Sowie Prze\u0142\u0119cz pod Szerok\u0105 na GSS Nowiu\u015bka, postawiona przez Nadle\u015bnictwo Bardo chyba jesieni\u0105 2016. Wygl\u0105da na szczeln\u0105, ale przewiewna - cho\u0107 miejsce jest w miar\u0119 os\u0142oni\u0119te od wiatru. Da si\u0119 spa\u0107 na stole, byle si\u0119 nie wierci\u0107 ;) O wodzie lepiej pomy\u015ble\u0107 wcze\u015bniej. Miejsce na ognisko - raczej jeszcze nie ma. 50.604976, 16.597770", "type": "wiata", "location": {"lon": "16.59777", "lat": "50.604976"}}, "_id": "X-blr2wBa0yzZ7_GaE9j"}, {"_index": "wiaty1", "_type": "_doc", "_score": 1.0, "_source": {"name": "G\u00f3ry Sowie Wigancicka Polana na GSS Lokal ciasny (max 2 osoby, je\u015bli wyniesie si\u0119 ze \u015brodka \u0142awy), szczelny od g\u00f3ry, przewiewny przy ziemi; obok zacny stela\u017c np. na tarpa. Woda - w Nied\u017awiedzim Potoku, przy drodze schodz\u0105cej na po\u0142udnie (czasem przysycha); miejsce na ogie\u0144 - bezpieczne. 50.631729, 16.565428", "type": "wiata", "location": {"lon": "16.565428", "lat": "50.631729"}}, "_id": "aOblr2wBa0yzZ7_GaE-d"}, {"_index": "wiaty1", "_type": "_doc", "_score": 1.0, "_source": {"name": "EDIT: XI 2018: wie\u017ca by\u0142a rozebrana ale obecnie postawiono now\u0105 G\u00f3ry Z\u0142ote, Jawornik Wielki /872m npm/. Wie\u017ca widokowa z dachem i podestami drewnianymi (jakby pi\u0119trowa wiata ;-)). Barierki a\u017curowe, wi\u0119c mo\u017ce wia\u0107. Wody w pobli\u017cu nie stwierdzono. (Zdj\u0119cie sprzed wycinki.) 50.406791, 16.850500", "type": "wiata", "location": {"lon": "16.8505", "lat": "50.406791"}}, "_id": "beblr2wBa0yzZ7_GaE-9"}, {"_index": "wiaty1", "_type": "_doc", "_score": 1.0, "_source": {"name": "G\u00f3ry Bardzkie,Srebrna G\u00f3ra, szlak czerwony ko\u0142o wiaduktu na Srebrnej Prze\u0142\u0119czy.Szeroko\u015b\u0107 50.57003 D\u0142ugo\u015b\u0107 16.63692", "type": "wiata", "location": {"lon": "16.63692", "lat": "50.57003"}}, "_id": "jOblr2wBa0yzZ7_GaU-T"}, {"_index": "wiaty1", "_type": "_doc", "_score": 1.0, "_source": {"name": "G\u00f3ry Orlickie 50.354829,16.424079 pa\u015bnik z mo\u017cliwo\u015bci\u0105 noclegu woda w rzece blisko", "type": "wiata", "location": {"lon": "16.424079", "lat": "50.354829"}}, "_id": "uOblr2wBa0yzZ7_Gak_R"}, {"_index": "wiaty1", "_type": "_doc", "_score": 1.0, "_source": {"name": "G\u00f3ry Bystrzyckie. Stok Kamiennej G\u00f3ry /704/ - na zielonym szlaku pomi\u0119dzy rozdro\u017cem z czerwonym a stok\u00f3wk\u0105. Fajna koleba skalna. Mniej wi\u0119cej: 50.374564, 16.499818", "type": "wiata", "location": {"lon": "16.499818", "lat": "50.374564"}}, "_id": "Oublr2wBa0yzZ7_GblAg"}, {"_index": "wiaty1", "_type": "_doc", "_score": 1.0, "_source": {"name": "G\u00f3ry Sto\u0142owe. Chociesz\u00f3w/Niwa/Wolany. Wiata przy \u0142\u0105ce ko\u0142o szosy do Batorowa, parking dla samochod\u00f3w i rowerowy 50m od wiaty. W \u015brodku 2 sto\u0142y 35x150, mi\u0119dzy nie wci\u015bnie si\u0119 namiot 2os. Obok sto\u0142y, \u0142awy, ognisko, \u015bmietnik. Woda: potok w dolinie, 170m, nie sprawdzono czy zdatna do picia. 50.446705, 16.494055", "type": "wiata", "location": {"lon": "16.494055", "lat": "50.446705"}}, "_id": "Reblr2wBa0yzZ7_GblBd"}, {"_index": "wiaty1", "_type": "_doc", "_score": 1.0, "_source": {"name": "G\u00f3ry Bystrzyckie. Wiata przy Torfowisku pod Ziele\u0144cem. Stoi bezpo\u015brednio przy drodze, kt\u00f3r\u0105 biegnie szlak zielony: 50.347338, 16.407410", "type": "wiata", "location": {"lon": "16.40741", "lat": "50.347338"}}, "_id": "Rublr2wBa0yzZ7_GblBj"}, {"_index": "wiaty1", "_type": "_doc", "_score": 1.0, "_source": {"name": "G\u00f3ry Bardzkie, przy samym parkingu na Prze\u0142\u0119czy K\u0142odzkiej, dok\u0142adnie tutaj https://www.google.com/maps/d/viewer\u2026 znajduje si\u0119 licha bo licha, badziewna bo badziewna ale jednak wiatka. Na trawniczku da\u0142o by si\u0119 chyba te\u017c spokojnie rozbi\u0107 namiot. Znajduje si\u0119 tam te\u017c nie tyle miejsce na ognisko co \u015blady po ognisku. Wody w pobli\u017cu nie zarejestrowa\u0142em- w stron\u0119 K\u0142odzkiej G\u00f3ry nie napotka\u0142em wody przez ca\u0142e kilometry. By\u0107 mo\u017ce w przeciwn\u0105 stron\u0119 niebieskim szlakiem co\u015b si\u0119 znajdzie. Pod\u0142oga wiatki to mocno uszkodzona betonowo-brukowa mozaika. Przez to, \u017ce taka pouszkadzana- spanie na tym to mo\u017ce by\u0107 tortura. \u0141awka w\u0105ska jak na spanie. 50.431438 16.765030", "type": "wiata", "location": {"lon": "16.76503", "lat": "50.431438"}}, "_id": "R-blr2wBa0yzZ7_GblBo"}, {"_index": "wiaty1", "_type": "_doc", "_score": 1.0, "_source": {"name": "Sudety, G\u00f3ry Bardzkie, Prze\u0142\u0119cz \u0141aszczowa, dwie bli\u017aniacze wiaty. Druga, niewidoczna na zdj\u0119ciu, znajduje si\u0119 kilkana\u015bcie metr\u00f3w obok po prawej stronie od przedstawionej. Przez prze\u0142\u0119cz prowadzi droga lokalna z K\u0142odzka do Lask\u00f3wki. 50.4759194 16.7366406", "type": "wiata", "location": {"lon": "16.736641", "lat": "50.475919"}}, "_id": "Seblr2wBa0yzZ7_GblBz"}, {"_index": "wiaty1", "_type": "_doc", "_score": 1.0, "_source": {"name": "Wiata po\u0142o\u017cona przy niebieskim szlaku rowerowym prowadz\u0105cym z miejscowo\u015bci Bila Voda w Czechach na Prze\u0142\u0119cz R\u00f3\u017caniec, poni\u017cej pieszego szlaku czerwonego.Jest miejsce na ognisko.Jak wida\u0107 na zdj\u0119ciu st\u00f3\u0142 w wiacie mo\u017ce by\u0107 dobr\u0105 izolacj\u0105 od pod\u0142o\u017ca podczas noclegu dla maksymalnie 1 osoby.", "type": "wiata", "location": {"lon": "16.878653", "lat": "50.414985"}}, "_id": "jeblr2wBa0yzZ7_Gb1D1"}, {"_index": "wiaty1", "_type": "_doc", "_score": 1.0, "_source": {"name": "Nowa wiatka grillowa na zielonym, przy parkingu. Jaka\u015b taka niziutka :-). Nie wiem, czy w sezonie letnim kasuj\u0105 na tym parkingu, bo obok stoi jakowa\u015b budka?", "type": "wiata", "location": {"lon": "16.918691", "lat": "50.370228"}}, "_id": "r-blr2wBa0yzZ7_GcFC2"}, {"_index": "wiaty1", "_type": "_doc", "_score": 1.0, "_source": {"name": "Wiata w lesie na stok\u00f3wce tzw. Drodze Malinowej przy podej\u015bciu na Trojak.", "type": "wiata", "location": {"lon": "16.9001743", "lat": "50.342073"}}, "_id": "sOblr2wBa0yzZ7_GcFC7"}, {"_index": "wiaty1", "_type": "_doc", "_score": 1.0, "_source": {"name": "Wiata na zielonym szlaku ko\u0142o kaplicy Matki Bo\u017cej od Zagubionych. Przed noclegiem radz\u0119 sprawdzi\u0107, czy nie wypada jakie\u015b katolickie \u015bwi\u0119to, poniewa\u017c wiatka jest wykorzystywana jako os\u0142ona o\u0142tarza polowego i czasem s\u0105 tam msze (np pasterka). Obok metalowy \u015bmietnik, \u0142awki, sto\u0142y, miejsce na ognicho. Woda w potoku przewijaj\u0105cym si\u0119 przez drog\u0119 jakie\u015b 150 metr\u00f3w ni\u017cej.", "type": "wiata", "location": {"lon": "16.923718", "lat": "50.338226"}}, "_id": "seblr2wBa0yzZ7_GcFDB"}, {"_index": "wiaty1", "_type": "_doc", "_score": 1.0, "_source": {"name": "Zadaszenie. 40 m obok potok.", "type": "wiata", "location": {"lon": "16.499692", "lat": "50.369767"}}, "_id": "t-blr2wBa0yzZ7_GcFDm"}, {"_index": "wiaty1", "_type": "_doc", "_score": 1.0, "_source": {"name": "miedzy \u017bdanowem a Wilcz\u0105, na poludnie od Srebrnej Gory. Dosc przewiewna (sam dach) wiata z ceglanym kominkiem. Na miejscu kosze na smieci i miejsce na ognisko chyba tez.", "type": "wiata", "location": {"lon": "16.664715", "lat": "50.543933"}}, "_id": "1eblr2wBa0yzZ7_GcVCa"}, {"_index": "wiaty1", "_type": "_doc", "_score": 1.0, "_source": {"name": "Wiata zaraz przy szosie i parkingu, zdarzaj\u0105 si\u0119 niestety wizyty na crossach itp. \"atrakcje\". Miejsce na ognisko. Woda by\u0142a gdzie\u015b poni\u017cej prze\u0142\u0119czy, niestety nie pami\u0119tam dok\u0142adnie. 50.623670, 16.587965", "type": "wiata", "location": {"lon": "16.587965", "lat": "50.62367"}}, "_id": "2eblr2wBa0yzZ7_GcVC0"}, {"_index": "wiaty1", "_type": "_doc", "_score": 1.0, "_source": {"name": "Wie\u017ca widokowa, \u0142awy, miejsce na ognisko. 50.358866, 16.665017", "type": "wiata", "location": {"lon": "16.665017", "lat": "50.358866"}}, "_id": "3-blr2wBa0yzZ7_GcVDW"}, {"_index": "wiaty1", "_type": "_doc", "_score": 1.0, "_source": {"name": "Sudety. Wiata przy drodze ze Zlotego Stoku w kierunku na L\u0105dek. Po prawej stronie drogi. Dosyc blisko asfaltowej drogi, ale w miare os\u0142oni\u0119ta. W oddali widac zabudowania jednego z przysiolkow. W wiacie jest kominek, jest miejsce na ognisko. Miejsce dosyc popularne - kilka razy spalismy tam, ale tez kilka razy sie odbilismy bo bylo zajete i musielismy jechac dalej. Wiata posiada dwie sciany i \u0142awy na tyle szerokie, ze mozna na nich spac.", "type": "wiata", "location": {"lon": "16.851005", "lat": "50.432696"}}, "_id": "6Oblr2wBa0yzZ7_GclAJ"}, {"_index": "wiaty1", "_type": "_doc", "_score": 1.0, "_source": {"name": "Koordynaty: 50.3364017, 16.4342522 Ganek domku my\u015bliwskiego przy polanie \u015bw. Huberta. Domek zamkni\u0119ty na g\u0142ucho, ale ganek jest do\u015b\u0107 mocno zadaszony, tak\u017ce jako awaryjne schronienie jak znalaz\u0142. Miejsce na ognisko na polanie obok domku.Wody brak.", "type": "wiata", "location": {"lon": "16.434252", "lat": "50.336402"}}, "_id": "Zeblr2wBa0yzZ7_GdFHQ"}, {"_index": "wiaty1", "_type": "_doc", "_score": 1.0, "_source": {"name": "50.35916 16.46305 Wiatka jak na zdj\u0119ciach, nic szczeg\u00f3lnego, ale przespa\u0107 si\u0119 mo\u017cna jak kto ch\u0119tny lub potrzebuj\u0105cy. Woda 50m w strumieniu. Odleg\u0142o\u015b\u0107 od zielonego szlaku jakie\u015b 150m.", "type": "wiata", "location": {"lon": "16.46305", "lat": "50.35916"}}, "_id": "eeblr2wBa0yzZ7_GdVFH"}, {"_index": "wiaty1", "_type": "_doc", "_score": 1.0, "_source": {"name": "50\u00b025'49.0\"N 16\u00b052'13.2\"E 50.430265, 16.870322 Wiata przy o\u015brodku Z\u0142oty Jar. Woda w strumieniu, Miejsce na ognicho.", "type": "wiata", "location": {"lon": "16.870322", "lat": "50.430265"}}, "_id": "p-blr2wBa0yzZ7_GdlFJ"}, {"_index": "wiaty1", "_type": "_doc", "_score": 1.0, "_source": {"name": "50\u00b024'48.3\"N 16\u00b048'58.3\"E 50.413405, 16.816200", "type": "wiata", "location": {"lon": "16.8162", "lat": "50.413405"}}, "_id": "qOblr2wBa0yzZ7_GdlFO"}, {"_index": "wiaty1", "_type": "_doc", "_score": 1.0, "_source": {"name": "50\u00b023'57.6\"N 16\u00b050'31.9\"E 50.399334, 16.842194", "type": "wiata", "location": {"lon": "16.842194", "lat": "50.399334"}}, "_id": "qublr2wBa0yzZ7_GdlFa"}, {"_index": "wiaty1", "_type": "_doc", "_score": 1.0, "_source": {"name": "50\u00b024'50.3\"N 16\u00b050'39.9\"E 50.413966, 16.844410", "type": "wiata", "location": {"lon": "16.8444101", "lat": "50.4135284"}}, "_id": "q-blr2wBa0yzZ7_GdlFg"}, {"_index": "wiaty1", "_type": "_doc", "_score": 1.0, "_source": {"name": "Zadaszona, otwarta od zachodu wiata, bez wody ale widokowa. W \u015brodku \u0142awka. Miejsce noclegowe dla 2 os\u00f3b. GPS: 50\u00b022'08.6\"N 16\u00b059'33.3\"E", "type": "wiata", "location": {"lon": "16.992583", "lat": "50.369056"}}, "_id": "xublr2wBa0yzZ7_GdlH-"}, {"_index": "wiaty1", "_type": "_doc", "_score": 1.0, "_source": {"name": "wiata niedaleko potoku Przy czerwonym szlaku serduszkowym", "type": "wiata", "location": {"lon": "16.4916900000001", "lat": "50.392217"}}, "_id": "-Oblr2wBa0yzZ7_GeFEg"}, {"_index": "wiaty1", "_type": "_doc", "_score": 1.0, "_source": {"name": "Wiata przy spalonej chacie niedaleko fortu Fryderyka Miejsce na ognicho jest, \u015amietniki i wog\u00f3le wypas", "type": "wiata", "location": {"lon": "16.4906570000001", "lat": "50.378839"}}, "_id": "-eblr2wBa0yzZ7_GeFEl"}, {"_index": "wiaty1", "_type": "_doc", "_score": 1.0, "_source": {"name": "Ruiny sa po\u0142ozone niedaleko g\u0142\u00f3wnej drogi, acz za rzeczk\u0105 i latem sa tak zaro\u015bniete, ze z drogi zupe\u0142nie niewidoczne. 50.444486, 16.833225 Wydaj\u0105 sie byc dogodnym miejscem noclegowym dla rowerzyst\u00f3w czy autostopowicz\u00f3w podr\u00f3\u017cuj\u0105cych drog\u0105 nr 46 na trasie K\u0142odzko - Z\u0142oty Stok. Dla zmotoryzowanych raczej nie - nie ma jak dojechac do ruin samochodem. Ruiny zawieraj\u0105 kilka zadaszonych kom\u00f3r, na ich podlodze sa li\u015bcie, czasem siano, lub ga\u0142\u0119zie. Raczej wszedzie jest czysto, ma\u0142o \u015bmieci. W niektorych komorach sa w scianach haki rokuj\u0105ce powieszenie hamaka. Mimo blisko\u015bci drogi ognisko mozna palic i bedzie z drogi niewidoczne, s\u0105 spore \"dziedzi\u0144ce\" otoczone wysokim murem dooko\u0142a.", "type": "wiata", "location": {"lon": "16.833225", "lat": "50.444486"}}, "_id": "NOblr2wBa0yzZ7_GeVJj"}, {"_index": "wiaty1", "_type": "_doc", "_score": 1.0, "_source": {"name": "50.4129393, 16.7978278", "type": "wiata", "location": {"lon": "16.7978278000001", "lat": "50.4129393"}}, "_id": "5eblr2wBa0yzZ7_GfVJR"}, {"_index": "wiaty1", "_type": "_doc", "_score": 1.0, "_source": {"name": "G\u00f3ry Kamienne / G\u00f3ry Suche / W\u0142odzicka G\u00f3ra / \u015awierki Dolne", "type": "wiata", "location": {"lon": "16.4318292", "lat": "50.6276544"}}, "_id": "GOblr2wBa0yzZ7_GflNf"}, {"_index": "wiaty1", "_type": "_doc", "_score": 1.0, "_source": {"name": "G\u00f3ry Sowie, Prze\u0142\u0119cz Srebrna, wiata", "type": "wiata", "location": {"lon": "16.6363", "lat": "50.57058"}}, "_id": "M-blr2wBa0yzZ7_GiVWh"}, {"_index": "wiaty1", "_type": "_doc", "_score": 1.0, "_source": {"name": "G\u00f3ry Sowie Bielawska Polana na GSS", "type": "wiata", "location": {"lon": "16.553283", "lat": "50.636513"}}, "_id": "WOblr2wBa0yzZ7_GilVw"}, {"_index": "wiaty1", "_type": "_doc", "_score": 1.0, "_source": {"name": "G\u00f3ry Z\u0142ote, opodal L\u0105dka-Zdroju", "type": "wiata", "location": {"lon": "16.898801", "lat": "50.342073"}}, "_id": "cublr2wBa0yzZ7_Gi1UW"}, {"_index": "wiaty1", "_type": "_doc", "_score": 1.0, "_source": {"name": "G\u00f3ry z\u0142ote, Chatka na bia\u0142ej g\u00f3rze", "type": "wiata", "location": {"lon": "16.851029", "lat": "50.432715"}}, "_id": "g-blr2wBa0yzZ7_Gi1WK"}, {"_index": "wiaty1", "_type": "_doc", "_score": 1.0, "_source": {"name": "G\u00f3ry z\u0142ote, prze\u0142\u0119cz pod Trzeboniem", "type": "wiata", "location": {"lon": "16.84441", "lat": "50.413966"}}, "_id": "hOblr2wBa0yzZ7_Gi1WQ"}, {"_index": "wiaty1", "_type": "_doc", "_score": 1.0, "_source": {"name": "G\u00f3ry Sowie, Prze\u0142\u0119cz Srebrna, wiata", "type": "wiata", "location": {"lon": "16.6363", "lat": "50.57058"}}, "_id": "oOblr2wBa0yzZ7_GjFU_"}, {"_index": "wiaty1", "_type": "_doc", "_score": 1.0, "_source": {"name": "G\u00f3ry Sowie Bielawska Polana na GSS", "type": "wiata", "location": {"lon": "16.553283", "lat": "50.636513"}}, "_id": "xeblr2wBa0yzZ7_GjVU6"}, {"_index": "wiaty1", "_type": "_doc", "_score": 1.0, "_source": {"name": "G\u00f3ry Z\u0142ote, opodal L\u0105dka-Zdroju", "type": "wiata", "location": {"lon": "16.898801", "lat": "50.342073"}}, "_id": "3-blr2wBa0yzZ7_GjVXI"}, {"_index": "wiaty1", "_type": "_doc", "_score": 1.0, "_source": {"name": "G\u00f3ry z\u0142ote, Chatka na bia\u0142ej g\u00f3rze", "type": "wiata", "location": {"lon": "16.851029", "lat": "50.432715"}}, "_id": "8eblr2wBa0yzZ7_GjlUe"}, {"_index": "wiaty1", "_type": "_doc", "_score": 1.0, "_source": {"name": "G\u00f3ry z\u0142ote, prze\u0142\u0119cz pod Trzeboniem", "type": "wiata", "location": {"lon": "16.84441", "lat": "50.413966"}}, "_id": "8ublr2wBa0yzZ7_GjlUj"}]}
